<?xml version="1.0" encoding="UTF-8"?>
<mesh>
    <sharedgeometry vertexcount="396">
        <vertexbuffer texture_coords="0" colours_diffuse="False" positions="true" normals="true">
            <vertex>
                <position z="0.643142" x="0.004924" y="0.000000"/>
                <normal z="0.984681" x="0.173834" y="-0.013598"/>
            </vertex>
            <vertex>
                <position z="0.643260" x="0.004431" y="0.002191"/>
                <normal z="0.984681" x="0.173834" y="-0.013598"/>
            </vertex>
            <vertex>
                <position z="0.643562" x="0.002867" y="0.004072"/>
                <normal z="0.984681" x="0.173834" y="-0.013598"/>
            </vertex>
            <vertex>
                <position z="0.643562" x="0.002867" y="0.004072"/>
                <normal z="0.984666" x="0.173925" y="-0.013551"/>
            </vertex>
            <vertex>
                <position z="0.643952" x="0.000727" y="0.004947"/>
                <normal z="0.984666" x="0.173925" y="-0.013551"/>
            </vertex>
            <vertex>
                <position z="0.643142" x="0.004924" y="0.000000"/>
                <normal z="0.984666" x="0.173925" y="-0.013551"/>
            </vertex>
            <vertex>
                <position z="0.643952" x="0.000727" y="0.004947"/>
                <normal z="0.984678" x="0.173853" y="-0.013613"/>
            </vertex>
            <vertex>
                <position z="0.644360" x="-0.001601" y="0.004724"/>
                <normal z="0.984678" x="0.173853" y="-0.013613"/>
            </vertex>
            <vertex>
                <position z="0.643142" x="0.004924" y="0.000000"/>
                <normal z="0.984678" x="0.173853" y="-0.013613"/>
            </vertex>
            <vertex>
                <position z="0.644360" x="-0.001601" y="0.004724"/>
                <normal z="0.984672" x="0.173887" y="-0.013565"/>
            </vertex>
            <vertex>
                <position z="0.644676" x="-0.003489" y="0.003519"/>
                <normal z="0.984672" x="0.173887" y="-0.013565"/>
            </vertex>
            <vertex>
                <position z="0.643142" x="0.004924" y="0.000000"/>
                <normal z="0.984672" x="0.173887" y="-0.013565"/>
            </vertex>
            <vertex>
                <position z="0.644676" x="-0.003489" y="0.003519"/>
                <normal z="0.984672" x="0.173887" y="-0.013564"/>
            </vertex>
            <vertex>
                <position z="0.644857" x="-0.004660" y="0.001602"/>
                <normal z="0.984672" x="0.173887" y="-0.013564"/>
            </vertex>
            <vertex>
                <position z="0.643142" x="0.004924" y="0.000000"/>
                <normal z="0.984672" x="0.173887" y="-0.013564"/>
            </vertex>
            <vertex>
                <position z="0.644857" x="-0.004660" y="0.001602"/>
                <normal z="0.984672" x="0.173888" y="-0.013559"/>
            </vertex>
            <vertex>
                <position z="0.644862" x="-0.004873" y="-0.000728"/>
                <normal z="0.984672" x="0.173888" y="-0.013559"/>
            </vertex>
            <vertex>
                <position z="0.643142" x="0.004924" y="0.000000"/>
                <normal z="0.984672" x="0.173888" y="-0.013559"/>
            </vertex>
            <vertex>
                <position z="0.644862" x="-0.004873" y="-0.000728"/>
                <normal z="0.984672" x="0.173889" y="-0.013574"/>
            </vertex>
            <vertex>
                <position z="0.644667" x="-0.003946" y="-0.003000"/>
                <normal z="0.984672" x="0.173889" y="-0.013574"/>
            </vertex>
            <vertex>
                <position z="0.643142" x="0.004924" y="0.000000"/>
                <normal z="0.984672" x="0.173889" y="-0.013574"/>
            </vertex>
            <vertex>
                <position z="0.644667" x="-0.003946" y="-0.003000"/>
                <normal z="0.984672" x="0.173888" y="-0.013571"/>
            </vertex>
            <vertex>
                <position z="0.644334" x="-0.002178" y="-0.004489"/>
                <normal z="0.984672" x="0.173888" y="-0.013571"/>
            </vertex>
            <vertex>
                <position z="0.643142" x="0.004924" y="0.000000"/>
                <normal z="0.984672" x="0.173888" y="-0.013571"/>
            </vertex>
            <vertex>
                <position z="0.644334" x="-0.002178" y="-0.004489"/>
                <normal z="0.984672" x="0.173889" y="-0.013573"/>
            </vertex>
            <vertex>
                <position z="0.643945" x="-0.000012" y="-0.005000"/>
                <normal z="0.984672" x="0.173889" y="-0.013573"/>
            </vertex>
            <vertex>
                <position z="0.643142" x="0.004924" y="0.000000"/>
                <normal z="0.984672" x="0.173889" y="-0.013573"/>
            </vertex>
            <vertex>
                <position z="0.643945" x="-0.000012" y="-0.005000"/>
                <normal z="0.984675" x="0.173874" y="-0.013558"/>
            </vertex>
            <vertex>
                <position z="0.643543" x="0.002309" y="-0.004410"/>
                <normal z="0.984675" x="0.173874" y="-0.013558"/>
            </vertex>
            <vertex>
                <position z="0.643142" x="0.004924" y="0.000000"/>
                <normal z="0.984675" x="0.173874" y="-0.013558"/>
            </vertex>
            <vertex>
                <position z="0.643543" x="0.002309" y="-0.004410"/>
                <normal z="0.984682" x="0.173832" y="-0.013532"/>
            </vertex>
            <vertex>
                <position z="0.643276" x="0.003932" y="-0.003000"/>
                <normal z="0.984682" x="0.173832" y="-0.013532"/>
            </vertex>
            <vertex>
                <position z="0.643142" x="0.004924" y="0.000000"/>
                <normal z="0.984682" x="0.173832" y="-0.013532"/>
            </vertex>
            <vertex>
                <position z="0.643276" x="0.003932" y="-0.003000"/>
                <normal z="0.984727" x="0.173586" y="-0.013449"/>
            </vertex>
            <vertex>
                <position z="0.643144" x="0.004851" y="-0.000842"/>
                <normal z="0.984727" x="0.173586" y="-0.013449"/>
            </vertex>
            <vertex>
                <position z="0.643142" x="0.004924" y="0.000000"/>
                <normal z="0.984727" x="0.173586" y="-0.013449"/>
            </vertex>
            <vertex>
                <position z="0.088458" x="-0.004967" y="-0.000459"/>
                <normal z="0.000157" x="-0.939309" y="-0.343071"/>
            </vertex>
            <vertex>
                <position z="0.088615" x="-0.004048" y="-0.002977"/>
                <normal z="0.000157" x="-0.939309" y="-0.343071"/>
            </vertex>
            <vertex>
                <position z="0.644667" x="-0.003946" y="-0.003000"/>
                <normal z="0.000157" x="-0.939309" y="-0.343071"/>
            </vertex>
            <vertex>
                <position z="0.644667" x="-0.003946" y="-0.003000"/>
                <normal z="-0.000026" x="-0.925911" y="-0.377743"/>
            </vertex>
            <vertex>
                <position z="0.644862" x="-0.004873" y="-0.000728"/>
                <normal z="-0.000026" x="-0.925911" y="-0.377743"/>
            </vertex>
            <vertex>
                <position z="0.088458" x="-0.004967" y="-0.000459"/>
                <normal z="-0.000026" x="-0.925911" y="-0.377743"/>
            </vertex>
            <vertex>
                <position z="0.644334" x="-0.002178" y="-0.004489"/>
                <normal z="0.000086" x="-0.644207" y="-0.764851"/>
            </vertex>
            <vertex>
                <position z="0.644667" x="-0.003946" y="-0.003000"/>
                <normal z="0.000086" x="-0.644207" y="-0.764851"/>
            </vertex>
            <vertex>
                <position z="0.088615" x="-0.004048" y="-0.002977"/>
                <normal z="0.000086" x="-0.644207" y="-0.764851"/>
            </vertex>
            <vertex>
                <position z="0.088615" x="-0.004048" y="-0.002977"/>
                <normal z="0.000109" x="-0.648237" y="-0.761439"/>
            </vertex>
            <vertex>
                <position z="0.089162" x="-0.002393" y="-0.004385"/>
                <normal z="0.000109" x="-0.648237" y="-0.761439"/>
            </vertex>
            <vertex>
                <position z="0.644334" x="-0.002178" y="-0.004489"/>
                <normal z="0.000109" x="-0.648237" y="-0.761439"/>
            </vertex>
            <vertex>
                <position z="0.089162" x="-0.002393" y="-0.004385"/>
                <normal z="0.000327" x="-0.320505" y="-0.947247"/>
            </vertex>
            <vertex>
                <position z="0.089452" x="-0.000494" y="-0.005028"/>
                <normal z="0.000327" x="-0.320505" y="-0.947247"/>
            </vertex>
            <vertex>
                <position z="0.643945" x="-0.000012" y="-0.005000"/>
                <normal z="0.000327" x="-0.320505" y="-0.947247"/>
            </vertex>
            <vertex>
                <position z="0.643945" x="-0.000012" y="-0.005000"/>
                <normal z="-0.000093" x="-0.229329" y="-0.973349"/>
            </vertex>
            <vertex>
                <position z="0.644334" x="-0.002178" y="-0.004489"/>
                <normal z="-0.000093" x="-0.229329" y="-0.973349"/>
            </vertex>
            <vertex>
                <position z="0.089162" x="-0.002393" y="-0.004385"/>
                <normal z="-0.000093" x="-0.229329" y="-0.973349"/>
            </vertex>
            <vertex>
                <position z="0.089388" x="0.000755" y="-0.004933"/>
                <normal z="0.000031" x="0.309112" y="-0.951025"/>
            </vertex>
            <vertex>
                <position z="0.089222" x="0.002230" y="-0.004454"/>
                <normal z="0.000031" x="0.309112" y="-0.951025"/>
            </vertex>
            <vertex>
                <position z="0.643543" x="0.002309" y="-0.004410"/>
                <normal z="0.000031" x="0.309112" y="-0.951025"/>
            </vertex>
            <vertex>
                <position z="0.089452" x="-0.000494" y="-0.005028"/>
                <normal z="0.000730" x="0.075330" y="-0.997158"/>
            </vertex>
            <vertex>
                <position z="0.089388" x="0.000755" y="-0.004933"/>
                <normal z="0.000730" x="0.075330" y="-0.997158"/>
            </vertex>
            <vertex>
                <position z="0.643543" x="0.002309" y="-0.004410"/>
                <normal z="0.000730" x="0.075330" y="-0.997158"/>
            </vertex>
            <vertex>
                <position z="0.643543" x="0.002309" y="-0.004410"/>
                <normal z="-0.000165" x="0.246127" y="-0.969238"/>
            </vertex>
            <vertex>
                <position z="0.643945" x="-0.000012" y="-0.005000"/>
                <normal z="-0.000165" x="0.246127" y="-0.969238"/>
            </vertex>
            <vertex>
                <position z="0.089452" x="-0.000494" y="-0.005028"/>
                <normal z="-0.000165" x="0.246127" y="-0.969238"/>
            </vertex>
            <vertex>
                <position z="0.089222" x="0.002230" y="-0.004454"/>
                <normal z="0.000229" x="0.605513" y="-0.795835"/>
            </vertex>
            <vertex>
                <position z="0.089003" x="0.003709" y="-0.003329"/>
                <normal z="0.000229" x="0.605513" y="-0.795835"/>
            </vertex>
            <vertex>
                <position z="0.643276" x="0.003932" y="-0.003000"/>
                <normal z="0.000229" x="0.605513" y="-0.795835"/>
            </vertex>
            <vertex>
                <position z="0.643276" x="0.003932" y="-0.003000"/>
                <normal z="-0.000034" x="0.655928" y="-0.754824"/>
            </vertex>
            <vertex>
                <position z="0.643543" x="0.002309" y="-0.004410"/>
                <normal z="-0.000034" x="0.655928" y="-0.754824"/>
            </vertex>
            <vertex>
                <position z="0.089222" x="0.002230" y="-0.004454"/>
                <normal z="-0.000034" x="0.655928" y="-0.754824"/>
            </vertex>
            <vertex>
                <position z="0.643144" x="0.004851" y="-0.000842"/>
                <normal z="-0.000105" x="0.964898" y="-0.262625"/>
            </vertex>
            <vertex>
                <position z="0.088846" x="0.004415" y="-0.002224"/>
                <normal z="-0.000105" x="0.964898" y="-0.262625"/>
            </vertex>
            <vertex>
                <position z="0.088630" x="0.004967" y="-0.000198"/>
                <normal z="-0.000105" x="0.964898" y="-0.262625"/>
            </vertex>
            <vertex>
                <position z="0.643144" x="0.004851" y="-0.000842"/>
                <normal z="-0.000138" x="0.919937" y="-0.392066"/>
            </vertex>
            <vertex>
                <position z="0.643276" x="0.003932" y="-0.003000"/>
                <normal z="-0.000138" x="0.919937" y="-0.392066"/>
            </vertex>
            <vertex>
                <position z="0.089003" x="0.003709" y="-0.003329"/>
                <normal z="-0.000138" x="0.919937" y="-0.392066"/>
            </vertex>
            <vertex>
                <position z="0.089003" x="0.003709" y="-0.003329"/>
                <normal z="0.000679" x="0.842563" y="-0.538598"/>
            </vertex>
            <vertex>
                <position z="0.088846" x="0.004415" y="-0.002224"/>
                <normal z="0.000679" x="0.842563" y="-0.538598"/>
            </vertex>
            <vertex>
                <position z="0.643144" x="0.004851" y="-0.000842"/>
                <normal z="0.000679" x="0.842563" y="-0.538598"/>
            </vertex>
            <vertex>
                <position z="0.643260" x="0.004431" y="0.002191"/>
                <normal z="-0.000003" x="0.975628" y="0.219432"/>
            </vertex>
            <vertex>
                <position z="0.643142" x="0.004924" y="0.000000"/>
                <normal z="-0.000003" x="0.975628" y="0.219432"/>
            </vertex>
            <vertex>
                <position z="0.088630" x="0.004967" y="-0.000198"/>
                <normal z="-0.000003" x="0.975628" y="0.219432"/>
            </vertex>
            <vertex>
                <position z="0.088630" x="0.004967" y="-0.000198"/>
                <normal z="0.000348" x="0.990000" y="0.141065"/>
            </vertex>
            <vertex>
                <position z="0.088846" x="0.004708" y="0.001619"/>
                <normal z="0.000348" x="0.990000" y="0.141065"/>
            </vertex>
            <vertex>
                <position z="0.643260" x="0.004431" y="0.002191"/>
                <normal z="0.000348" x="0.990000" y="0.141065"/>
            </vertex>
            <vertex>
                <position z="0.088911" x="0.003692" y="0.003221"/>
                <normal z="0.000162" x="0.768863" y="0.639414"/>
            </vertex>
            <vertex>
                <position z="0.643562" x="0.002867" y="0.004072"/>
                <normal z="0.000162" x="0.768863" y="0.639414"/>
            </vertex>
            <vertex>
                <position z="0.643260" x="0.004431" y="0.002191"/>
                <normal z="0.000162" x="0.768863" y="0.639414"/>
            </vertex>
            <vertex>
                <position z="0.088911" x="0.003692" y="0.003221"/>
                <normal z="-0.000130" x="0.674270" y="0.738485"/>
            </vertex>
            <vertex>
                <position z="0.089179" x="0.002486" y="0.004321"/>
                <normal z="-0.000130" x="0.674270" y="0.738485"/>
            </vertex>
            <vertex>
                <position z="0.643562" x="0.002867" y="0.004072"/>
                <normal z="-0.000130" x="0.674270" y="0.738485"/>
            </vertex>
            <vertex>
                <position z="0.643952" x="0.000727" y="0.004947"/>
                <normal z="0.000074" x="0.355358" y="0.934730"/>
            </vertex>
            <vertex>
                <position z="0.089179" x="0.002486" y="0.004321"/>
                <normal z="0.000074" x="0.355358" y="0.934730"/>
            </vertex>
            <vertex>
                <position z="0.089335" x="0.000936" y="0.004911"/>
                <normal z="0.000074" x="0.355358" y="0.934730"/>
            </vertex>
            <vertex>
                <position z="0.089179" x="0.002486" y="0.004321"/>
                <normal z="0.000157" x="0.378435" y="0.925628"/>
            </vertex>
            <vertex>
                <position z="0.643952" x="0.000727" y="0.004947"/>
                <normal z="0.000157" x="0.378435" y="0.925628"/>
            </vertex>
            <vertex>
                <position z="0.643562" x="0.002867" y="0.004072"/>
                <normal z="0.000157" x="0.378435" y="0.925628"/>
            </vertex>
            <vertex>
                <position z="0.644360" x="-0.001601" y="0.004724"/>
                <normal z="-0.000114" x="-0.305076" y="0.952328"/>
            </vertex>
            <vertex>
                <position z="0.089321" x="-0.000694" y="0.004948"/>
                <normal z="-0.000114" x="-0.305076" y="0.952328"/>
            </vertex>
            <vertex>
                <position z="0.089089" x="-0.002211" y="0.004462"/>
                <normal z="-0.000114" x="-0.305076" y="0.952328"/>
            </vertex>
            <vertex>
                <position z="0.089321" x="-0.000694" y="0.004948"/>
                <normal z="0.000246" x="-0.095068" y="0.995471"/>
            </vertex>
            <vertex>
                <position z="0.644360" x="-0.001601" y="0.004724"/>
                <normal z="0.000246" x="-0.095068" y="0.995471"/>
            </vertex>
            <vertex>
                <position z="0.643952" x="0.000727" y="0.004947"/>
                <normal z="0.000246" x="-0.095068" y="0.995471"/>
            </vertex>
            <vertex>
                <position z="0.643952" x="0.000727" y="0.004947"/>
                <normal z="-0.000056" x="0.022733" y="0.999742"/>
            </vertex>
            <vertex>
                <position z="0.089335" x="0.000936" y="0.004911"/>
                <normal z="-0.000056" x="0.022733" y="0.999742"/>
            </vertex>
            <vertex>
                <position z="0.089321" x="-0.000694" y="0.004948"/>
                <normal z="-0.000056" x="0.022733" y="0.999742"/>
            </vertex>
            <vertex>
                <position z="0.644676" x="-0.003489" y="0.003519"/>
                <normal z="0.000193" x="-0.537869" y="0.843028"/>
            </vertex>
            <vertex>
                <position z="0.644360" x="-0.001601" y="0.004724"/>
                <normal z="0.000193" x="-0.537869" y="0.843028"/>
            </vertex>
            <vertex>
                <position z="0.089089" x="-0.002211" y="0.004462"/>
                <normal z="0.000193" x="-0.537869" y="0.843028"/>
            </vertex>
            <vertex>
                <position z="0.644857" x="-0.004660" y="0.001602"/>
                <normal z="-0.000001" x="-0.853345" y="0.521348"/>
            </vertex>
            <vertex>
                <position z="0.644676" x="-0.003489" y="0.003519"/>
                <normal z="-0.000001" x="-0.853345" y="0.521348"/>
            </vertex>
            <vertex>
                <position z="0.089056" x="-0.003491" y="0.003515"/>
                <normal z="-0.000001" x="-0.853345" y="0.521348"/>
            </vertex>
            <vertex>
                <position z="0.089056" x="-0.003491" y="0.003515"/>
                <normal z="0.000165" x="-0.831131" y="0.556077"/>
            </vertex>
            <vertex>
                <position z="0.088812" x="-0.004583" y="0.001882"/>
                <normal z="0.000165" x="-0.831131" y="0.556077"/>
            </vertex>
            <vertex>
                <position z="0.644857" x="-0.004660" y="0.001602"/>
                <normal z="0.000165" x="-0.831131" y="0.556077"/>
            </vertex>
            <vertex>
                <position z="0.644857" x="-0.004660" y="0.001602"/>
                <normal z="-0.000055" x="-0.986823" y="0.161804"/>
            </vertex>
            <vertex>
                <position z="0.088812" x="-0.004583" y="0.001882"/>
                <normal z="-0.000055" x="-0.986823" y="0.161804"/>
            </vertex>
            <vertex>
                <position z="0.088458" x="-0.004967" y="-0.000459"/>
                <normal z="-0.000055" x="-0.986823" y="0.161804"/>
            </vertex>
            <vertex>
                <position z="0.088458" x="-0.004967" y="-0.000459"/>
                <normal z="0.000212" x="-0.995857" y="0.090930"/>
            </vertex>
            <vertex>
                <position z="0.644862" x="-0.004873" y="-0.000728"/>
                <normal z="0.000212" x="-0.995857" y="0.090930"/>
            </vertex>
            <vertex>
                <position z="0.644857" x="-0.004660" y="0.001602"/>
                <normal z="0.000212" x="-0.995857" y="0.090930"/>
            </vertex>
            <vertex>
                <position z="0.089089" x="-0.002211" y="0.004462"/>
                <normal z="-0.000004" x="-0.594630" y="0.804000"/>
            </vertex>
            <vertex>
                <position z="0.089056" x="-0.003491" y="0.003515"/>
                <normal z="-0.000004" x="-0.594630" y="0.804000"/>
            </vertex>
            <vertex>
                <position z="0.644676" x="-0.003489" y="0.003519"/>
                <normal z="-0.000004" x="-0.594630" y="0.804000"/>
            </vertex>
            <vertex>
                <position z="0.088846" x="0.004708" y="0.001619"/>
                <normal z="-0.000131" x="0.844493" y="0.535567"/>
            </vertex>
            <vertex>
                <position z="0.088911" x="0.003692" y="0.003221"/>
                <normal z="-0.000131" x="0.844493" y="0.535567"/>
            </vertex>
            <vertex>
                <position z="0.643260" x="0.004431" y="0.002191"/>
                <normal z="-0.000131" x="0.844493" y="0.535567"/>
            </vertex>
            <vertex>
                <position z="0.088630" x="0.004967" y="-0.000198"/>
                <normal z="0.000107" x="0.996330" y="-0.085593"/>
            </vertex>
            <vertex>
                <position z="0.643142" x="0.004924" y="0.000000"/>
                <normal z="0.000107" x="0.996330" y="-0.085593"/>
            </vertex>
            <vertex>
                <position z="0.643144" x="0.004851" y="-0.000842"/>
                <normal z="0.000107" x="0.996330" y="-0.085593"/>
            </vertex>
            <vertex>
                <position z="-0.078354" x="-0.005069" y="0.095851"/>
                <normal z="-0.592757" x="-0.795099" y="-0.128283"/>
            </vertex>
            <vertex>
                <position z="-0.083795" x="-0.001608" y="0.099537"/>
                <normal z="-0.592757" x="-0.795099" y="-0.128283"/>
            </vertex>
            <vertex>
                <position z="-0.079484" x="-0.003717" y="0.092691"/>
                <normal z="-0.592757" x="-0.795099" y="-0.128283"/>
            </vertex>
            <vertex>
                <position z="-0.078277" x="0.005063" y="0.095541"/>
                <normal z="0.174629" x="0.935487" y="0.307194"/>
            </vertex>
            <vertex>
                <position z="-0.073074" x="0.003582" y="0.097092"/>
                <normal z="0.174629" x="0.935487" y="0.307194"/>
            </vertex>
            <vertex>
                <position z="0.088846" x="0.004708" y="0.001619"/>
                <normal z="0.174629" x="0.935487" y="0.307194"/>
            </vertex>
            <vertex>
                <position z="-0.077065" x="-0.000068" y="0.089404"/>
                <normal z="-0.475058" x="-0.221972" y="-0.851498"/>
            </vertex>
            <vertex>
                <position z="-0.083349" x="0.002360" y="0.092277"/>
                <normal z="-0.475058" x="-0.221972" y="-0.851498"/>
            </vertex>
            <vertex>
                <position z="0.081322" x="0.003904" y="0.000003"/>
                <normal z="-0.475058" x="-0.221972" y="-0.851498"/>
            </vertex>
            <vertex>
                <position z="-0.083795" x="-0.001608" y="0.099537"/>
                <normal z="0.079518" x="0.285640" y="0.955032"/>
            </vertex>
            <vertex>
                <position z="-0.071641" x="0.000072" y="0.098023"/>
                <normal z="0.079518" x="0.285640" y="0.955032"/>
            </vertex>
            <vertex>
                <position z="-0.073074" x="0.003582" y="0.097092"/>
                <normal z="0.079518" x="0.285640" y="0.955032"/>
            </vertex>
            <vertex>
                <position z="-0.083795" x="-0.001608" y="0.099537"/>
                <normal z="0.089121" x="-0.657114" y="0.748504"/>
            </vertex>
            <vertex>
                <position z="-0.078354" x="-0.005069" y="0.095851"/>
                <normal z="0.089121" x="-0.657114" y="0.748504"/>
            </vertex>
            <vertex>
                <position z="-0.071854" x="-0.003682" y="0.096294"/>
                <normal z="0.089121" x="-0.657114" y="0.748504"/>
            </vertex>
            <vertex>
                <position z="-0.071854" x="-0.003682" y="0.096294"/>
                <normal z="0.169165" x="-0.420109" y="0.891567"/>
            </vertex>
            <vertex>
                <position z="-0.071641" x="0.000072" y="0.098023"/>
                <normal z="0.169165" x="-0.420109" y="0.891567"/>
            </vertex>
            <vertex>
                <position z="-0.083795" x="-0.001608" y="0.099537"/>
                <normal z="0.169165" x="-0.420109" y="0.891567"/>
            </vertex>
            <vertex>
                <position z="-0.078277" x="0.005063" y="0.095541"/>
                <normal z="-0.144600" x="0.593773" y="0.791533"/>
            </vertex>
            <vertex>
                <position z="-0.087147" x="0.005076" y="0.093911"/>
                <normal z="-0.144600" x="0.593773" y="0.791533"/>
            </vertex>
            <vertex>
                <position z="-0.083795" x="-0.001608" y="0.099537"/>
                <normal z="-0.144600" x="0.593773" y="0.791533"/>
            </vertex>
            <vertex>
                <position z="-0.079484" x="-0.003717" y="0.092691"/>
                <normal z="0.522722" x="-0.735201" y="-0.431557"/>
            </vertex>
            <vertex>
                <position z="-0.084587" x="-0.003772" y="0.086604"/>
                <normal z="0.522722" x="-0.735201" y="-0.431557"/>
            </vertex>
            <vertex>
                <position z="-0.077065" x="-0.000068" y="0.089404"/>
                <normal z="0.522722" x="-0.735201" y="-0.431557"/>
            </vertex>
            <vertex>
                <position z="-0.083795" x="-0.001608" y="0.099537"/>
                <normal z="-0.612506" x="-0.675219" y="0.410995"/>
            </vertex>
            <vertex>
                <position z="-0.093104" x="-0.000613" y="0.087297"/>
                <normal z="-0.612506" x="-0.675219" y="0.410995"/>
            </vertex>
            <vertex>
                <position z="-0.089812" x="-0.004878" y="0.085197"/>
                <normal z="-0.612506" x="-0.675219" y="0.410995"/>
            </vertex>
            <vertex>
                <position z="-0.079484" x="-0.003717" y="0.092691"/>
                <normal z="0.255165" x="-0.944844" y="-0.205329"/>
            </vertex>
            <vertex>
                <position z="-0.089812" x="-0.004878" y="0.085197"/>
                <normal z="0.255165" x="-0.944844" y="-0.205329"/>
            </vertex>
            <vertex>
                <position z="-0.084587" x="-0.003772" y="0.086604"/>
                <normal z="0.255165" x="-0.944844" y="-0.205329"/>
            </vertex>
            <vertex>
                <position z="-0.087147" x="0.005076" y="0.093911"/>
                <normal z="-0.781401" x="0.593297" y="0.193419"/>
            </vertex>
            <vertex>
                <position z="-0.091740" x="0.003306" y="0.080790"/>
                <normal z="-0.781401" x="0.593297" y="0.193419"/>
            </vertex>
            <vertex>
                <position z="-0.093104" x="-0.000613" y="0.087297"/>
                <normal z="-0.781401" x="0.593297" y="0.193419"/>
            </vertex>
            <vertex>
                <position z="-0.091740" x="0.003306" y="0.080790"/>
                <normal z="-0.367692" x="0.929942" y="0.003200"/>
            </vertex>
            <vertex>
                <position z="-0.087147" x="0.005076" y="0.093911"/>
                <normal z="-0.367692" x="0.929942" y="0.003200"/>
            </vertex>
            <vertex>
                <position z="-0.090835" x="0.004238" y="-0.086256"/>
                <normal z="-0.367692" x="0.929942" y="0.003200"/>
            </vertex>
            <vertex>
                <position z="-0.083115" x="-0.001131" y="0.083401"/>
                <normal z="0.997757" x="0.066943" y="-0.000003"/>
            </vertex>
            <vertex>
                <position z="-0.083114" x="-0.001152" y="-0.084987"/>
                <normal z="0.997757" x="0.066943" y="-0.000003"/>
            </vertex>
            <vertex>
                <position z="-0.083349" x="0.002360" y="0.092277"/>
                <normal z="0.997757" x="0.066943" y="-0.000003"/>
            </vertex>
            <vertex>
                <position z="-0.083349" x="0.002360" y="0.092277"/>
                <normal z="0.581587" x="0.813484" y="-0.000199"/>
            </vertex>
            <vertex>
                <position z="-0.083450" x="0.002388" y="-0.089233"/>
                <normal z="0.581587" x="0.813484" y="-0.000199"/>
            </vertex>
            <vertex>
                <position z="-0.087147" x="0.005076" y="0.093911"/>
                <normal z="0.581587" x="0.813484" y="-0.000199"/>
            </vertex>
            <vertex>
                <position z="0.088812" x="-0.004583" y="0.001882"/>
                <normal z="0.177831" x="-0.933447" y="0.311533"/>
            </vertex>
            <vertex>
                <position z="-0.071854" x="-0.003682" y="0.096294"/>
                <normal z="0.177831" x="-0.933447" y="0.311533"/>
            </vertex>
            <vertex>
                <position z="-0.078354" x="-0.005069" y="0.095851"/>
                <normal z="0.177831" x="-0.933447" y="0.311533"/>
            </vertex>
            <vertex>
                <position z="0.089056" x="-0.003491" y="0.003515"/>
                <normal z="0.418647" x="-0.546978" y="0.724948"/>
            </vertex>
            <vertex>
                <position z="0.089089" x="-0.002211" y="0.004462"/>
                <normal z="0.418647" x="-0.546978" y="0.724948"/>
            </vertex>
            <vertex>
                <position z="-0.071854" x="-0.003682" y="0.096294"/>
                <normal z="0.418647" x="-0.546978" y="0.724948"/>
            </vertex>
            <vertex>
                <position z="-0.071854" x="-0.003682" y="0.096294"/>
                <normal z="0.290346" x="-0.814750" y="0.501877"/>
            </vertex>
            <vertex>
                <position z="0.088812" x="-0.004583" y="0.001882"/>
                <normal z="0.290346" x="-0.814750" y="0.501877"/>
            </vertex>
            <vertex>
                <position z="0.089056" x="-0.003491" y="0.003515"/>
                <normal z="0.290346" x="-0.814750" y="0.501877"/>
            </vertex>
            <vertex>
                <position z="0.089089" x="-0.002211" y="0.004462"/>
                <normal z="0.458412" x="-0.393036" y="0.797108"/>
            </vertex>
            <vertex>
                <position z="-0.071641" x="0.000072" y="0.098023"/>
                <normal z="0.458412" x="-0.393036" y="0.797108"/>
            </vertex>
            <vertex>
                <position z="-0.071854" x="-0.003682" y="0.096294"/>
                <normal z="0.458412" x="-0.393036" y="0.797108"/>
            </vertex>
            <vertex>
                <position z="-0.071641" x="0.000072" y="0.098023"/>
                <normal z="0.500571" x="0.015565" y="0.865556"/>
            </vertex>
            <vertex>
                <position z="0.089321" x="-0.000694" y="0.004948"/>
                <normal z="0.500571" x="0.015565" y="0.865556"/>
            </vertex>
            <vertex>
                <position z="0.089335" x="0.000936" y="0.004911"/>
                <normal z="0.500571" x="0.015565" y="0.865556"/>
            </vertex>
            <vertex>
                <position z="-0.071641" x="0.000072" y="0.098023"/>
                <normal z="0.470675" x="-0.333795" y="0.816729"/>
            </vertex>
            <vertex>
                <position z="0.089089" x="-0.002211" y="0.004462"/>
                <normal z="0.470675" x="-0.333795" y="0.816729"/>
            </vertex>
            <vertex>
                <position z="0.089321" x="-0.000694" y="0.004948"/>
                <normal z="0.470675" x="-0.333795" y="0.816729"/>
            </vertex>
            <vertex>
                <position z="-0.073074" x="0.003582" y="0.097092"/>
                <normal z="0.457805" x="0.397658" y="0.795162"/>
            </vertex>
            <vertex>
                <position z="-0.071641" x="0.000072" y="0.098023"/>
                <normal z="0.457805" x="0.397658" y="0.795162"/>
            </vertex>
            <vertex>
                <position z="0.089335" x="0.000936" y="0.004911"/>
                <normal z="0.457805" x="0.397658" y="0.795162"/>
            </vertex>
            <vertex>
                <position z="0.089335" x="0.000936" y="0.004911"/>
                <normal z="0.465866" x="0.354836" y="0.810593"/>
            </vertex>
            <vertex>
                <position z="0.089179" x="0.002486" y="0.004321"/>
                <normal z="0.465866" x="0.354836" y="0.810593"/>
            </vertex>
            <vertex>
                <position z="-0.073074" x="0.003582" y="0.097092"/>
                <normal z="0.465866" x="0.354836" y="0.810593"/>
            </vertex>
            <vertex>
                <position z="0.088846" x="0.004708" y="0.001619"/>
                <normal z="0.291473" x="0.813088" y="0.503916"/>
            </vertex>
            <vertex>
                <position z="-0.073074" x="0.003582" y="0.097092"/>
                <normal z="0.291473" x="0.813088" y="0.503916"/>
            </vertex>
            <vertex>
                <position z="0.088911" x="0.003692" y="0.003221"/>
                <normal z="0.291473" x="0.813088" y="0.503916"/>
            </vertex>
            <vertex>
                <position z="0.088630" x="0.004967" y="-0.000198"/>
                <normal z="-0.145948" x="0.955757" y="-0.255399"/>
            </vertex>
            <vertex>
                <position z="0.081322" x="0.003904" y="0.000003"/>
                <normal z="-0.145948" x="0.955757" y="-0.255399"/>
            </vertex>
            <vertex>
                <position z="-0.078277" x="0.005063" y="0.095541"/>
                <normal z="-0.145948" x="0.955757" y="-0.255399"/>
            </vertex>
            <vertex>
                <position z="-0.079484" x="-0.003717" y="0.092691"/>
                <normal z="-0.457319" x="-0.408396" y="-0.789982"/>
            </vertex>
            <vertex>
                <position z="-0.077065" x="-0.000068" y="0.089404"/>
                <normal z="-0.457319" x="-0.408396" y="-0.789982"/>
            </vertex>
            <vertex>
                <position z="0.077450" x="-0.000204" y="0.000026"/>
                <normal z="-0.457319" x="-0.408396" y="-0.789982"/>
            </vertex>
            <vertex>
                <position z="0.088812" x="-0.004583" y="0.001882"/>
                <normal z="0.086318" x="-0.985143" y="0.148469"/>
            </vertex>
            <vertex>
                <position z="-0.078354" x="-0.005069" y="0.095851"/>
                <normal z="0.086318" x="-0.985143" y="0.148469"/>
            </vertex>
            <vertex>
                <position z="0.088458" x="-0.004967" y="-0.000459"/>
                <normal z="0.086318" x="-0.985143" y="0.148469"/>
            </vertex>
            <vertex>
                <position z="0.081831" x="-0.003921" y="0.000011"/>
                <normal z="-0.169391" x="-0.940556" y="-0.294383"/>
            </vertex>
            <vertex>
                <position z="0.088458" x="-0.004967" y="-0.000459"/>
                <normal z="-0.169391" x="-0.940556" y="-0.294383"/>
            </vertex>
            <vertex>
                <position z="-0.078354" x="-0.005069" y="0.095851"/>
                <normal z="-0.169391" x="-0.940556" y="-0.294383"/>
            </vertex>
            <vertex>
                <position z="0.077450" x="-0.000204" y="0.000026"/>
                <normal z="-0.430589" x="-0.504533" y="-0.748358"/>
            </vertex>
            <vertex>
                <position z="0.081831" x="-0.003921" y="0.000011"/>
                <normal z="-0.430589" x="-0.504533" y="-0.748358"/>
            </vertex>
            <vertex>
                <position z="-0.079484" x="-0.003717" y="0.092691"/>
                <normal z="-0.430589" x="-0.504533" y="-0.748358"/>
            </vertex>
            <vertex>
                <position z="0.077450" x="-0.000204" y="0.000026"/>
                <normal z="-0.453428" x="0.423009" y="-0.784517"/>
            </vertex>
            <vertex>
                <position z="-0.077065" x="-0.000068" y="0.089404"/>
                <normal z="-0.453428" x="0.423009" y="-0.784517"/>
            </vertex>
            <vertex>
                <position z="0.081322" x="0.003904" y="0.000003"/>
                <normal z="-0.453428" x="0.423009" y="-0.784517"/>
            </vertex>
            <vertex>
                <position z="0.089179" x="0.002486" y="0.004321"/>
                <normal z="0.372008" x="0.669717" y="0.642720"/>
            </vertex>
            <vertex>
                <position z="0.088911" x="0.003692" y="0.003221"/>
                <normal z="0.372008" x="0.669717" y="0.642720"/>
            </vertex>
            <vertex>
                <position z="-0.073074" x="0.003582" y="0.097092"/>
                <normal z="0.372008" x="0.669717" y="0.642720"/>
            </vertex>
            <vertex>
                <position z="-0.084587" x="-0.003772" y="0.086604"/>
                <normal z="0.873615" x="-0.486618" y="0.000063"/>
            </vertex>
            <vertex>
                <position z="-0.083114" x="-0.001152" y="-0.084987"/>
                <normal z="0.873615" x="-0.486618" y="0.000063"/>
            </vertex>
            <vertex>
                <position z="-0.083115" x="-0.001131" y="0.083401"/>
                <normal z="0.873615" x="-0.486618" y="0.000063"/>
            </vertex>
            <vertex>
                <position z="-0.089812" x="-0.004878" y="0.085197"/>
                <normal z="0.206213" x="-0.978503" y="0.002884"/>
            </vertex>
            <vertex>
                <position z="-0.085386" x="-0.004467" y="-0.091872"/>
                <normal z="0.206213" x="-0.978503" y="0.002884"/>
            </vertex>
            <vertex>
                <position z="-0.084587" x="-0.003772" y="0.086604"/>
                <normal z="0.206213" x="-0.978503" y="0.002884"/>
            </vertex>
            <vertex>
                <position z="-0.083349" x="0.002360" y="0.092277"/>
                <normal z="0.930876" x="-0.330941" y="0.154749"/>
            </vertex>
            <vertex>
                <position z="-0.084587" x="-0.003772" y="0.086604"/>
                <normal z="0.930876" x="-0.330941" y="0.154749"/>
            </vertex>
            <vertex>
                <position z="-0.083115" x="-0.001131" y="0.083401"/>
                <normal z="0.930876" x="-0.330941" y="0.154749"/>
            </vertex>
            <vertex>
                <position z="-0.093104" x="-0.000613" y="0.087297"/>
                <normal z="-0.785872" x="0.116955" y="0.607228"/>
            </vertex>
            <vertex>
                <position z="-0.083795" x="-0.001608" y="0.099537"/>
                <normal z="-0.785872" x="0.116955" y="0.607228"/>
            </vertex>
            <vertex>
                <position z="-0.087147" x="0.005076" y="0.093911"/>
                <normal z="-0.785872" x="0.116955" y="0.607228"/>
            </vertex>
            <vertex>
                <position z="-0.077065" x="-0.000068" y="0.089404"/>
                <normal z="-0.067065" x="0.684791" y="-0.725647"/>
            </vertex>
            <vertex>
                <position z="-0.084587" x="-0.003772" y="0.086604"/>
                <normal z="-0.067065" x="0.684791" y="-0.725647"/>
            </vertex>
            <vertex>
                <position z="-0.083349" x="0.002360" y="0.092277"/>
                <normal z="-0.067065" x="0.684791" y="-0.725647"/>
            </vertex>
            <vertex>
                <position z="-0.083795" x="-0.001608" y="0.099537"/>
                <normal z="-0.084930" x="0.562794" y="0.822222"/>
            </vertex>
            <vertex>
                <position z="-0.073074" x="0.003582" y="0.097092"/>
                <normal z="-0.084930" x="0.562794" y="0.822222"/>
            </vertex>
            <vertex>
                <position z="-0.078277" x="0.005063" y="0.095541"/>
                <normal z="-0.084930" x="0.562794" y="0.822222"/>
            </vertex>
            <vertex>
                <position z="-0.078277" x="0.005063" y="0.095541"/>
                <normal z="-0.225995" x="0.893365" y="-0.388362"/>
            </vertex>
            <vertex>
                <position z="0.081322" x="0.003904" y="0.000003"/>
                <normal z="-0.225995" x="0.893365" y="-0.388362"/>
            </vertex>
            <vertex>
                <position z="-0.083349" x="0.002360" y="0.092277"/>
                <normal z="-0.225995" x="0.893365" y="-0.388362"/>
            </vertex>
            <vertex>
                <position z="-0.079484" x="-0.003717" y="0.092691"/>
                <normal z="-0.189641" x="-0.925430" y="-0.328048"/>
            </vertex>
            <vertex>
                <position z="0.081831" x="-0.003921" y="0.000011"/>
                <normal z="-0.189641" x="-0.925430" y="-0.328048"/>
            </vertex>
            <vertex>
                <position z="-0.078354" x="-0.005069" y="0.095851"/>
                <normal z="-0.189641" x="-0.925430" y="-0.328048"/>
            </vertex>
            <vertex>
                <position z="0.088846" x="0.004708" y="0.001619"/>
                <normal z="0.076171" x="0.988345" y="0.131801"/>
            </vertex>
            <vertex>
                <position z="0.088630" x="0.004967" y="-0.000198"/>
                <normal z="0.076171" x="0.988345" y="0.131801"/>
            </vertex>
            <vertex>
                <position z="-0.078277" x="0.005063" y="0.095541"/>
                <normal z="0.076171" x="0.988345" y="0.131801"/>
            </vertex>
            <vertex>
                <position z="-0.089812" x="-0.004878" y="0.085197"/>
                <normal z="-0.073644" x="-0.965180" y="0.251008"/>
            </vertex>
            <vertex>
                <position z="-0.079484" x="-0.003717" y="0.092691"/>
                <normal z="-0.073644" x="-0.965180" y="0.251008"/>
            </vertex>
            <vertex>
                <position z="-0.083795" x="-0.001608" y="0.099537"/>
                <normal z="-0.073644" x="-0.965180" y="0.251008"/>
            </vertex>
            <vertex>
                <position z="-0.083349" x="0.002360" y="0.092277"/>
                <normal z="0.138990" x="0.645890" y="-0.750672"/>
            </vertex>
            <vertex>
                <position z="-0.087147" x="0.005076" y="0.093911"/>
                <normal z="0.138990" x="0.645890" y="-0.750672"/>
            </vertex>
            <vertex>
                <position z="-0.078277" x="0.005063" y="0.095541"/>
                <normal z="0.138990" x="0.645890" y="-0.750672"/>
            </vertex>
            <vertex>
                <position z="-0.087147" x="0.005076" y="0.093911"/>
                <normal z="-0.199381" x="0.979922" y="-0.000477"/>
            </vertex>
            <vertex>
                <position z="-0.086972" x="0.005022" y="-0.091387"/>
                <normal z="-0.199381" x="0.979922" y="-0.000477"/>
            </vertex>
            <vertex>
                <position z="-0.090835" x="0.004238" y="-0.086256"/>
                <normal z="-0.199381" x="0.979922" y="-0.000477"/>
            </vertex>
            <vertex>
                <position z="-0.093203" x="-0.001363" y="-0.085898"/>
                <normal z="-0.944834" x="0.327550" y="-0.000878"/>
            </vertex>
            <vertex>
                <position z="-0.093104" x="-0.000613" y="0.087297"/>
                <normal z="-0.944834" x="0.327550" y="-0.000878"/>
            </vertex>
            <vertex>
                <position z="-0.091740" x="0.003306" y="0.080790"/>
                <normal z="-0.944834" x="0.327550" y="-0.000878"/>
            </vertex>
            <vertex>
                <position z="-0.083349" x="0.002360" y="0.092277"/>
                <normal z="0.995588" x="0.093829" y="-0.000539"/>
            </vertex>
            <vertex>
                <position z="-0.083114" x="-0.001152" y="-0.084987"/>
                <normal z="0.995588" x="0.093829" y="-0.000539"/>
            </vertex>
            <vertex>
                <position z="-0.083450" x="0.002388" y="-0.089233"/>
                <normal z="0.995588" x="0.093829" y="-0.000539"/>
            </vertex>
            <vertex>
                <position z="-0.083450" x="0.002388" y="-0.089233"/>
                <normal z="0.598745" x="0.800939" y="0.000332"/>
            </vertex>
            <vertex>
                <position z="-0.086972" x="0.005022" y="-0.091387"/>
                <normal z="0.598745" x="0.800939" y="0.000332"/>
            </vertex>
            <vertex>
                <position z="-0.087147" x="0.005076" y="0.093911"/>
                <normal z="0.598745" x="0.800939" y="0.000332"/>
            </vertex>
            <vertex>
                <position z="-0.083114" x="-0.001152" y="-0.084987"/>
                <normal z="0.826361" x="-0.563138" y="-0.001511"/>
            </vertex>
            <vertex>
                <position z="-0.084587" x="-0.003772" y="0.086604"/>
                <normal z="0.826361" x="-0.563138" y="-0.001511"/>
            </vertex>
            <vertex>
                <position z="-0.085386" x="-0.004467" y="-0.091872"/>
                <normal z="0.826361" x="-0.563138" y="-0.001511"/>
            </vertex>
            <vertex>
                <position z="-0.086972" x="0.005022" y="-0.091387"/>
                <normal z="-0.720391" x="0.515837" y="-0.463626"/>
            </vertex>
            <vertex>
                <position z="-0.086001" x="0.000017" y="-0.098463"/>
                <normal z="-0.720391" x="0.515837" y="-0.463626"/>
            </vertex>
            <vertex>
                <position z="-0.090835" x="0.004238" y="-0.086256"/>
                <normal z="-0.720391" x="0.515837" y="-0.463626"/>
            </vertex>
            <vertex>
                <position z="-0.085386" x="-0.004467" y="-0.091872"/>
                <normal z="0.956477" x="-0.182444" y="-0.227742"/>
            </vertex>
            <vertex>
                <position z="-0.083450" x="0.002388" y="-0.089233"/>
                <normal z="0.956477" x="-0.182444" y="-0.227742"/>
            </vertex>
            <vertex>
                <position z="-0.083114" x="-0.001152" y="-0.084987"/>
                <normal z="0.956477" x="-0.182444" y="-0.227742"/>
            </vertex>
            <vertex>
                <position z="-0.086972" x="0.005022" y="-0.091387"/>
                <normal z="-0.315041" x="0.753958" y="-0.576452"/>
            </vertex>
            <vertex>
                <position z="-0.078880" x="0.005035" y="-0.095791"/>
                <normal z="-0.315041" x="0.753958" y="-0.576452"/>
            </vertex>
            <vertex>
                <position z="-0.086001" x="0.000017" y="-0.098463"/>
                <normal z="-0.315041" x="0.753958" y="-0.576452"/>
            </vertex>
            <vertex>
                <position z="-0.085386" x="-0.004467" y="-0.091872"/>
                <normal z="-0.367511" x="-0.784528" y="-0.499451"/>
            </vertex>
            <vertex>
                <position z="-0.086001" x="0.000017" y="-0.098463"/>
                <normal z="-0.367511" x="-0.784528" y="-0.499451"/>
            </vertex>
            <vertex>
                <position z="-0.079335" x="-0.005020" y="-0.095456"/>
                <normal z="-0.367511" x="-0.784528" y="-0.499451"/>
            </vertex>
            <vertex>
                <position z="-0.085386" x="-0.004467" y="-0.091872"/>
                <normal z="-0.118966" x="-0.327280" y="0.937409"/>
            </vertex>
            <vertex>
                <position z="-0.077209" x="-0.002171" y="-0.090033"/>
                <normal z="-0.118966" x="-0.327280" y="0.937409"/>
            </vertex>
            <vertex>
                <position z="-0.083450" x="0.002388" y="-0.089233"/>
                <normal z="-0.118966" x="-0.327280" y="0.937409"/>
            </vertex>
            <vertex>
                <position z="-0.086001" x="0.000017" y="-0.098463"/>
                <normal z="-0.077122" x="-0.751163" y="-0.655596"/>
            </vertex>
            <vertex>
                <position z="-0.072495" x="-0.001638" y="-0.098155"/>
                <normal z="-0.077122" x="-0.751163" y="-0.655596"/>
            </vertex>
            <vertex>
                <position z="-0.071367" x="-0.003822" y="-0.095785"/>
                <normal z="-0.077122" x="-0.751163" y="-0.655596"/>
            </vertex>
            <vertex>
                <position z="-0.077209" x="-0.002171" y="-0.090033"/>
                <normal z="0.160167" x="-0.898291" y="0.409170"/>
            </vertex>
            <vertex>
                <position z="-0.085386" x="-0.004467" y="-0.091872"/>
                <normal z="0.160167" x="-0.898291" y="0.409170"/>
            </vertex>
            <vertex>
                <position z="-0.079335" x="-0.005020" y="-0.095456"/>
                <normal z="0.160167" x="-0.898291" y="0.409170"/>
            </vertex>
            <vertex>
                <position z="-0.075054" x="0.003566" y="-0.089992"/>
                <normal z="0.045713" x="0.289859" y="0.955977"/>
            </vertex>
            <vertex>
                <position z="-0.083450" x="0.002388" y="-0.089233"/>
                <normal z="0.045713" x="0.289859" y="0.955977"/>
            </vertex>
            <vertex>
                <position z="-0.076253" x="0.001276" y="-0.089240"/>
                <normal z="0.045713" x="0.289859" y="0.955977"/>
            </vertex>
            <vertex>
                <position z="-0.076253" x="0.001276" y="-0.089240"/>
                <normal z="-0.032368" x="-0.215502" y="0.975967"/>
            </vertex>
            <vertex>
                <position z="-0.083450" x="0.002388" y="-0.089233"/>
                <normal z="-0.032368" x="-0.215502" y="0.975967"/>
            </vertex>
            <vertex>
                <position z="-0.077209" x="-0.002171" y="-0.090033"/>
                <normal z="-0.032368" x="-0.215502" y="0.975967"/>
            </vertex>
            <vertex>
                <position z="-0.075054" x="0.003566" y="-0.089992"/>
                <normal z="-0.437481" x="0.478710" y="0.761214"/>
            </vertex>
            <vertex>
                <position z="-0.076253" x="0.001276" y="-0.089240"/>
                <normal z="-0.437481" x="0.478710" y="0.761214"/>
            </vertex>
            <vertex>
                <position z="0.077450" x="-0.000204" y="0.000026"/>
                <normal z="-0.437481" x="0.478710" y="0.761214"/>
            </vertex>
            <vertex>
                <position z="-0.074165" x="0.003282" y="-0.097964"/>
                <normal z="0.280988" x="0.826260" y="-0.488201"/>
            </vertex>
            <vertex>
                <position z="0.088846" x="0.004415" y="-0.002224"/>
                <normal z="0.280988" x="0.826260" y="-0.488201"/>
            </vertex>
            <vertex>
                <position z="0.089003" x="0.003709" y="-0.003329"/>
                <normal z="0.280988" x="0.826260" y="-0.488201"/>
            </vertex>
            <vertex>
                <position z="0.088846" x="0.004415" y="-0.002224"/>
                <normal z="0.291758" x="0.811463" y="-0.506364"/>
            </vertex>
            <vertex>
                <position z="-0.074165" x="0.003282" y="-0.097964"/>
                <normal z="0.291758" x="0.811463" y="-0.506364"/>
            </vertex>
            <vertex>
                <position z="-0.072860" x="0.004583" y="-0.095127"/>
                <normal z="0.291758" x="0.811463" y="-0.506364"/>
            </vertex>
            <vertex>
                <position z="-0.074165" x="0.003282" y="-0.097964"/>
                <normal z="0.472160" x="0.319972" y="-0.821391"/>
            </vertex>
            <vertex>
                <position z="0.089222" x="0.002230" y="-0.004454"/>
                <normal z="0.472160" x="0.319972" y="-0.821391"/>
            </vertex>
            <vertex>
                <position z="0.089388" x="0.000755" y="-0.004933"/>
                <normal z="0.472160" x="0.319972" y="-0.821391"/>
            </vertex>
            <vertex>
                <position z="-0.074165" x="0.003282" y="-0.097964"/>
                <normal z="0.403510" x="0.591127" y="-0.698390"/>
            </vertex>
            <vertex>
                <position z="0.089003" x="0.003709" y="-0.003329"/>
                <normal z="0.403510" x="0.591127" y="-0.698390"/>
            </vertex>
            <vertex>
                <position z="0.089222" x="0.002230" y="-0.004454"/>
                <normal z="0.403510" x="0.591127" y="-0.698390"/>
            </vertex>
            <vertex>
                <position z="-0.072495" x="-0.001638" y="-0.098155"/>
                <normal z="0.495972" x="0.090575" y="-0.863602"/>
            </vertex>
            <vertex>
                <position z="0.089388" x="0.000755" y="-0.004933"/>
                <normal z="0.495972" x="0.090575" y="-0.863602"/>
            </vertex>
            <vertex>
                <position z="0.089452" x="-0.000494" y="-0.005028"/>
                <normal z="0.495972" x="0.090575" y="-0.863602"/>
            </vertex>
            <vertex>
                <position z="0.089388" x="0.000755" y="-0.004933"/>
                <normal z="0.499151" x="-0.024519" y="-0.866168"/>
            </vertex>
            <vertex>
                <position z="-0.072495" x="-0.001638" y="-0.098155"/>
                <normal z="0.499151" x="-0.024519" y="-0.866168"/>
            </vertex>
            <vertex>
                <position z="-0.073116" x="0.001249" y="-0.098594"/>
                <normal z="0.499151" x="-0.024519" y="-0.866168"/>
            </vertex>
            <vertex>
                <position z="-0.071367" x="-0.003822" y="-0.095785"/>
                <normal z="0.415429" x="-0.561642" y="-0.715526"/>
            </vertex>
            <vertex>
                <position z="-0.072495" x="-0.001638" y="-0.098155"/>
                <normal z="0.415429" x="-0.561642" y="-0.715526"/>
            </vertex>
            <vertex>
                <position z="0.089452" x="-0.000494" y="-0.005028"/>
                <normal z="0.415429" x="-0.561642" y="-0.715526"/>
            </vertex>
            <vertex>
                <position z="0.089452" x="-0.000494" y="-0.005028"/>
                <normal z="0.466449" x="-0.346590" y="-0.813819"/>
            </vertex>
            <vertex>
                <position z="0.089162" x="-0.002393" y="-0.004385"/>
                <normal z="0.466449" x="-0.346590" y="-0.813819"/>
            </vertex>
            <vertex>
                <position z="-0.071367" x="-0.003822" y="-0.095785"/>
                <normal z="0.466449" x="-0.346590" y="-0.813819"/>
            </vertex>
            <vertex>
                <position z="0.088458" x="-0.004967" y="-0.000459"/>
                <normal z="0.188158" x="-0.926248" y="-0.326591"/>
            </vertex>
            <vertex>
                <position z="-0.071367" x="-0.003822" y="-0.095785"/>
                <normal z="0.188158" x="-0.926248" y="-0.326591"/>
            </vertex>
            <vertex>
                <position z="0.088615" x="-0.004048" y="-0.002977"/>
                <normal z="0.188158" x="-0.926248" y="-0.326591"/>
            </vertex>
            <vertex>
                <position z="-0.079335" x="-0.005020" y="-0.095456"/>
                <normal z="-0.134915" x="-0.961641" y="0.238839"/>
            </vertex>
            <vertex>
                <position z="0.088458" x="-0.004967" y="-0.000459"/>
                <normal z="-0.134915" x="-0.961641" y="0.238839"/>
            </vertex>
            <vertex>
                <position z="0.081831" x="-0.003921" y="0.000011"/>
                <normal z="-0.134915" x="-0.961641" y="0.238839"/>
            </vertex>
            <vertex>
                <position z="-0.077209" x="-0.002171" y="-0.090033"/>
                <normal z="-0.428529" x="-0.508255" y="0.747020"/>
            </vertex>
            <vertex>
                <position z="0.081831" x="-0.003921" y="0.000011"/>
                <normal z="-0.428529" x="-0.508255" y="0.747020"/>
            </vertex>
            <vertex>
                <position z="0.077450" x="-0.000204" y="0.000026"/>
                <normal z="-0.428529" x="-0.508255" y="0.747020"/>
            </vertex>
            <vertex>
                <position z="0.088846" x="0.004415" y="-0.002224"/>
                <normal z="0.142226" x="0.958824" y="-0.245821"/>
            </vertex>
            <vertex>
                <position z="-0.072860" x="0.004583" y="-0.095127"/>
                <normal z="0.142226" x="0.958824" y="-0.245821"/>
            </vertex>
            <vertex>
                <position z="0.088630" x="0.004967" y="-0.000198"/>
                <normal z="0.142226" x="0.958824" y="-0.245821"/>
            </vertex>
            <vertex>
                <position z="0.081831" x="-0.003921" y="0.000011"/>
                <normal z="-0.311404" x="-0.785532" y="0.534759"/>
            </vertex>
            <vertex>
                <position z="-0.077209" x="-0.002171" y="-0.090033"/>
                <normal z="-0.311404" x="-0.785532" y="0.534759"/>
            </vertex>
            <vertex>
                <position z="-0.079335" x="-0.005020" y="-0.095456"/>
                <normal z="-0.311404" x="-0.785532" y="0.534759"/>
            </vertex>
            <vertex>
                <position z="0.089162" x="-0.002393" y="-0.004385"/>
                <normal z="0.371850" x="-0.669904" y="-0.642617"/>
            </vertex>
            <vertex>
                <position z="0.088615" x="-0.004048" y="-0.002977"/>
                <normal z="0.371850" x="-0.669904" y="-0.642617"/>
            </vertex>
            <vertex>
                <position z="-0.071367" x="-0.003822" y="-0.095785"/>
                <normal z="0.371850" x="-0.669904" y="-0.642617"/>
            </vertex>
            <vertex>
                <position z="0.089388" x="0.000755" y="-0.004933"/>
                <normal z="0.442883" x="0.466015" y="-0.765953"/>
            </vertex>
            <vertex>
                <position z="-0.073116" x="0.001249" y="-0.098594"/>
                <normal z="0.442883" x="0.466015" y="-0.765953"/>
            </vertex>
            <vertex>
                <position z="-0.074165" x="0.003282" y="-0.097964"/>
                <normal z="0.442883" x="0.466015" y="-0.765953"/>
            </vertex>
            <vertex>
                <position z="-0.078880" x="0.005035" y="-0.095791"/>
                <normal z="-0.215394" x="0.903357" y="0.370880"/>
            </vertex>
            <vertex>
                <position z="-0.075054" x="0.003566" y="-0.089992"/>
                <normal z="-0.215394" x="0.903357" y="0.370880"/>
            </vertex>
            <vertex>
                <position z="0.081322" x="0.003904" y="0.000003"/>
                <normal z="-0.215394" x="0.903357" y="0.370880"/>
            </vertex>
            <vertex>
                <position z="0.077450" x="-0.000204" y="0.000026"/>
                <normal z="-0.451150" x="0.429480" y="0.782311"/>
            </vertex>
            <vertex>
                <position z="0.081322" x="0.003904" y="0.000003"/>
                <normal z="-0.451150" x="0.429480" y="0.782311"/>
            </vertex>
            <vertex>
                <position z="-0.075054" x="0.003566" y="-0.089992"/>
                <normal z="-0.451150" x="0.429480" y="0.782311"/>
            </vertex>
            <vertex>
                <position z="-0.077209" x="-0.002171" y="-0.090033"/>
                <normal z="-0.501760" x="-0.059277" y="0.862974"/>
            </vertex>
            <vertex>
                <position z="0.077450" x="-0.000204" y="0.000026"/>
                <normal z="-0.501760" x="-0.059277" y="0.862974"/>
            </vertex>
            <vertex>
                <position z="-0.076253" x="0.001276" y="-0.089240"/>
                <normal z="-0.501760" x="-0.059277" y="0.862974"/>
            </vertex>
            <vertex>
                <position z="0.088458" x="-0.004967" y="-0.000459"/>
                <normal z="0.134803" x="-0.961973" y="-0.237564"/>
            </vertex>
            <vertex>
                <position z="-0.079335" x="-0.005020" y="-0.095456"/>
                <normal z="0.134803" x="-0.961973" y="-0.237564"/>
            </vertex>
            <vertex>
                <position z="-0.071367" x="-0.003822" y="-0.095785"/>
                <normal z="0.134803" x="-0.961973" y="-0.237564"/>
            </vertex>
            <vertex>
                <position z="-0.072860" x="0.004583" y="-0.095127"/>
                <normal z="0.091400" x="0.982965" y="-0.159454"/>
            </vertex>
            <vertex>
                <position z="-0.078880" x="0.005035" y="-0.095791"/>
                <normal z="0.091400" x="0.982965" y="-0.159454"/>
            </vertex>
            <vertex>
                <position z="0.088630" x="0.004967" y="-0.000198"/>
                <normal z="0.091400" x="0.982965" y="-0.159454"/>
            </vertex>
            <vertex>
                <position z="-0.072495" x="-0.001638" y="-0.098155"/>
                <normal z="0.004201" x="-0.149498" y="-0.988753"/>
            </vertex>
            <vertex>
                <position z="-0.086001" x="0.000017" y="-0.098463"/>
                <normal z="0.004201" x="-0.149498" y="-0.988753"/>
            </vertex>
            <vertex>
                <position z="-0.073116" x="0.001249" y="-0.098594"/>
                <normal z="0.004201" x="-0.149498" y="-0.988753"/>
            </vertex>
            <vertex>
                <position z="-0.071367" x="-0.003822" y="-0.095785"/>
                <normal z="0.035453" x="-0.477212" y="-0.878073"/>
            </vertex>
            <vertex>
                <position z="-0.079335" x="-0.005020" y="-0.095456"/>
                <normal z="0.035453" x="-0.477212" y="-0.878073"/>
            </vertex>
            <vertex>
                <position z="-0.086001" x="0.000017" y="-0.098463"/>
                <normal z="0.035453" x="-0.477212" y="-0.878073"/>
            </vertex>
            <vertex>
                <position z="-0.078880" x="0.005035" y="-0.095791"/>
                <normal z="0.116720" x="0.881299" y="-0.457918"/>
            </vertex>
            <vertex>
                <position z="-0.072860" x="0.004583" y="-0.095127"/>
                <normal z="0.116720" x="0.881299" y="-0.457918"/>
            </vertex>
            <vertex>
                <position z="-0.074165" x="0.003282" y="-0.097964"/>
                <normal z="0.116720" x="0.881299" y="-0.457918"/>
            </vertex>
            <vertex>
                <position z="-0.074165" x="0.003282" y="-0.097964"/>
                <normal z="-0.036446" x="0.278649" y="-0.959701"/>
            </vertex>
            <vertex>
                <position z="-0.073116" x="0.001249" y="-0.098594"/>
                <normal z="-0.036446" x="0.278649" y="-0.959701"/>
            </vertex>
            <vertex>
                <position z="-0.086001" x="0.000017" y="-0.098463"/>
                <normal z="-0.036446" x="0.278649" y="-0.959701"/>
            </vertex>
            <vertex>
                <position z="-0.074165" x="0.003282" y="-0.097964"/>
                <normal z="-0.134678" x="0.607751" y="-0.782624"/>
            </vertex>
            <vertex>
                <position z="-0.086001" x="0.000017" y="-0.098463"/>
                <normal z="-0.134678" x="0.607751" y="-0.782624"/>
            </vertex>
            <vertex>
                <position z="-0.078880" x="0.005035" y="-0.095791"/>
                <normal z="-0.134678" x="0.607751" y="-0.782624"/>
            </vertex>
            <vertex>
                <position z="-0.089812" x="-0.004878" y="0.085197"/>
                <normal z="-0.376606" x="-0.926301" y="-0.011563"/>
            </vertex>
            <vertex>
                <position z="-0.093203" x="-0.001363" y="-0.085898"/>
                <normal z="-0.376606" x="-0.926301" y="-0.011563"/>
            </vertex>
            <vertex>
                <position z="-0.085386" x="-0.004467" y="-0.091872"/>
                <normal z="-0.376606" x="-0.926301" y="-0.011563"/>
            </vertex>
            <vertex>
                <position z="-0.093203" x="-0.001363" y="-0.085898"/>
                <normal z="-0.591593" x="-0.691203" y="-0.415038"/>
            </vertex>
            <vertex>
                <position z="-0.086001" x="0.000017" y="-0.098463"/>
                <normal z="-0.591593" x="-0.691203" y="-0.415038"/>
            </vertex>
            <vertex>
                <position z="-0.085386" x="-0.004467" y="-0.091872"/>
                <normal z="-0.591593" x="-0.691203" y="-0.415038"/>
            </vertex>
            <vertex>
                <position z="-0.090835" x="0.004238" y="-0.086256"/>
                <normal z="-0.835451" x="0.324977" y="-0.443184"/>
            </vertex>
            <vertex>
                <position z="-0.086001" x="0.000017" y="-0.098463"/>
                <normal z="-0.835451" x="0.324977" y="-0.443184"/>
            </vertex>
            <vertex>
                <position z="-0.093203" x="-0.001363" y="-0.085898"/>
                <normal z="-0.835451" x="0.324977" y="-0.443184"/>
            </vertex>
            <vertex>
                <position z="-0.093203" x="-0.001363" y="-0.085898"/>
                <normal z="-0.790866" x="-0.611982" y="0.003104"/>
            </vertex>
            <vertex>
                <position z="-0.089812" x="-0.004878" y="0.085197"/>
                <normal z="-0.790866" x="-0.611982" y="0.003104"/>
            </vertex>
            <vertex>
                <position z="-0.093104" x="-0.000613" y="0.087297"/>
                <normal z="-0.790866" x="-0.611982" y="0.003104"/>
            </vertex>
            <vertex>
                <position z="-0.091740" x="0.003306" y="0.080790"/>
                <normal z="-0.921110" x="0.389292" y="-0.002816"/>
            </vertex>
            <vertex>
                <position z="-0.090835" x="0.004238" y="-0.086256"/>
                <normal z="-0.921110" x="0.389292" y="-0.002816"/>
            </vertex>
            <vertex>
                <position z="-0.093203" x="-0.001363" y="-0.085898"/>
                <normal z="-0.921110" x="0.389292" y="-0.002816"/>
            </vertex>
            <vertex>
                <position z="0.081322" x="0.003904" y="0.000003"/>
                <normal z="-0.133519" x="0.962864" y="0.234659"/>
            </vertex>
            <vertex>
                <position z="0.088630" x="0.004967" y="-0.000198"/>
                <normal z="-0.133519" x="0.962864" y="0.234659"/>
            </vertex>
            <vertex>
                <position z="-0.078880" x="0.005035" y="-0.095791"/>
                <normal z="-0.133519" x="0.962864" y="0.234659"/>
            </vertex>
            <vertex>
                <position z="-0.083450" x="0.002388" y="-0.089233"/>
                <normal z="-0.104779" x="0.945413" y="0.308571"/>
            </vertex>
            <vertex>
                <position z="-0.075054" x="0.003566" y="-0.089992"/>
                <normal z="-0.104779" x="0.945413" y="0.308571"/>
            </vertex>
            <vertex>
                <position z="-0.078880" x="0.005035" y="-0.095791"/>
                <normal z="-0.104779" x="0.945413" y="0.308571"/>
            </vertex>
            <vertex>
                <position z="-0.083450" x="0.002388" y="-0.089233"/>
                <normal z="0.282719" x="0.804808" y="0.521876"/>
            </vertex>
            <vertex>
                <position z="-0.078880" x="0.005035" y="-0.095791"/>
                <normal z="0.282719" x="0.804808" y="0.521876"/>
            </vertex>
            <vertex>
                <position z="-0.086972" x="0.005022" y="-0.091387"/>
                <normal z="0.282719" x="0.804808" y="0.521876"/>
            </vertex>
        </vertexbuffer>
    </sharedgeometry>
    <submeshes>
        <submesh material="_missing_material_" usesharedvertices="true" operationtype="triangle_list" use32bitindexes="False">
            <faces count="132">
                <face v3="2" v1="0" v2="1"/>
                <face v3="5" v1="3" v2="4"/>
                <face v3="8" v1="6" v2="7"/>
                <face v3="11" v1="9" v2="10"/>
                <face v3="14" v1="12" v2="13"/>
                <face v3="17" v1="15" v2="16"/>
                <face v3="20" v1="18" v2="19"/>
                <face v3="23" v1="21" v2="22"/>
                <face v3="26" v1="24" v2="25"/>
                <face v3="29" v1="27" v2="28"/>
                <face v3="32" v1="30" v2="31"/>
                <face v3="35" v1="33" v2="34"/>
                <face v3="38" v1="36" v2="37"/>
                <face v3="41" v1="39" v2="40"/>
                <face v3="44" v1="42" v2="43"/>
                <face v3="47" v1="45" v2="46"/>
                <face v3="50" v1="48" v2="49"/>
                <face v3="53" v1="51" v2="52"/>
                <face v3="56" v1="54" v2="55"/>
                <face v3="59" v1="57" v2="58"/>
                <face v3="62" v1="60" v2="61"/>
                <face v3="65" v1="63" v2="64"/>
                <face v3="68" v1="66" v2="67"/>
                <face v3="71" v1="69" v2="70"/>
                <face v3="74" v1="72" v2="73"/>
                <face v3="77" v1="75" v2="76"/>
                <face v3="80" v1="78" v2="79"/>
                <face v3="83" v1="81" v2="82"/>
                <face v3="86" v1="84" v2="85"/>
                <face v3="89" v1="87" v2="88"/>
                <face v3="92" v1="90" v2="91"/>
                <face v3="95" v1="93" v2="94"/>
                <face v3="98" v1="96" v2="97"/>
                <face v3="101" v1="99" v2="100"/>
                <face v3="104" v1="102" v2="103"/>
                <face v3="107" v1="105" v2="106"/>
                <face v3="110" v1="108" v2="109"/>
                <face v3="113" v1="111" v2="112"/>
                <face v3="116" v1="114" v2="115"/>
                <face v3="119" v1="117" v2="118"/>
                <face v3="122" v1="120" v2="121"/>
                <face v3="125" v1="123" v2="124"/>
                <face v3="128" v1="126" v2="127"/>
                <face v3="131" v1="129" v2="130"/>
                <face v3="134" v1="132" v2="133"/>
                <face v3="137" v1="135" v2="136"/>
                <face v3="140" v1="138" v2="139"/>
                <face v3="143" v1="141" v2="142"/>
                <face v3="146" v1="144" v2="145"/>
                <face v3="149" v1="147" v2="148"/>
                <face v3="152" v1="150" v2="151"/>
                <face v3="155" v1="153" v2="154"/>
                <face v3="158" v1="156" v2="157"/>
                <face v3="161" v1="159" v2="160"/>
                <face v3="164" v1="162" v2="163"/>
                <face v3="167" v1="165" v2="166"/>
                <face v3="170" v1="168" v2="169"/>
                <face v3="173" v1="171" v2="172"/>
                <face v3="176" v1="174" v2="175"/>
                <face v3="179" v1="177" v2="178"/>
                <face v3="182" v1="180" v2="181"/>
                <face v3="185" v1="183" v2="184"/>
                <face v3="188" v1="186" v2="187"/>
                <face v3="191" v1="189" v2="190"/>
                <face v3="194" v1="192" v2="193"/>
                <face v3="197" v1="195" v2="196"/>
                <face v3="200" v1="198" v2="199"/>
                <face v3="203" v1="201" v2="202"/>
                <face v3="206" v1="204" v2="205"/>
                <face v3="209" v1="207" v2="208"/>
                <face v3="212" v1="210" v2="211"/>
                <face v3="215" v1="213" v2="214"/>
                <face v3="218" v1="216" v2="217"/>
                <face v3="221" v1="219" v2="220"/>
                <face v3="224" v1="222" v2="223"/>
                <face v3="227" v1="225" v2="226"/>
                <face v3="230" v1="228" v2="229"/>
                <face v3="233" v1="231" v2="232"/>
                <face v3="236" v1="234" v2="235"/>
                <face v3="239" v1="237" v2="238"/>
                <face v3="242" v1="240" v2="241"/>
                <face v3="245" v1="243" v2="244"/>
                <face v3="248" v1="246" v2="247"/>
                <face v3="251" v1="249" v2="250"/>
                <face v3="254" v1="252" v2="253"/>
                <face v3="257" v1="255" v2="256"/>
                <face v3="260" v1="258" v2="259"/>
                <face v3="263" v1="261" v2="262"/>
                <face v3="266" v1="264" v2="265"/>
                <face v3="269" v1="267" v2="268"/>
                <face v3="272" v1="270" v2="271"/>
                <face v3="275" v1="273" v2="274"/>
                <face v3="278" v1="276" v2="277"/>
                <face v3="281" v1="279" v2="280"/>
                <face v3="284" v1="282" v2="283"/>
                <face v3="287" v1="285" v2="286"/>
                <face v3="290" v1="288" v2="289"/>
                <face v3="293" v1="291" v2="292"/>
                <face v3="296" v1="294" v2="295"/>
                <face v3="299" v1="297" v2="298"/>
                <face v3="302" v1="300" v2="301"/>
                <face v3="305" v1="303" v2="304"/>
                <face v3="308" v1="306" v2="307"/>
                <face v3="311" v1="309" v2="310"/>
                <face v3="314" v1="312" v2="313"/>
                <face v3="317" v1="315" v2="316"/>
                <face v3="320" v1="318" v2="319"/>
                <face v3="323" v1="321" v2="322"/>
                <face v3="326" v1="324" v2="325"/>
                <face v3="329" v1="327" v2="328"/>
                <face v3="332" v1="330" v2="331"/>
                <face v3="335" v1="333" v2="334"/>
                <face v3="338" v1="336" v2="337"/>
                <face v3="341" v1="339" v2="340"/>
                <face v3="344" v1="342" v2="343"/>
                <face v3="347" v1="345" v2="346"/>
                <face v3="350" v1="348" v2="349"/>
                <face v3="353" v1="351" v2="352"/>
                <face v3="356" v1="354" v2="355"/>
                <face v3="359" v1="357" v2="358"/>
                <face v3="362" v1="360" v2="361"/>
                <face v3="365" v1="363" v2="364"/>
                <face v3="368" v1="366" v2="367"/>
                <face v3="371" v1="369" v2="370"/>
                <face v3="374" v1="372" v2="373"/>
                <face v3="377" v1="375" v2="376"/>
                <face v3="380" v1="378" v2="379"/>
                <face v3="383" v1="381" v2="382"/>
                <face v3="386" v1="384" v2="385"/>
                <face v3="389" v1="387" v2="388"/>
                <face v3="392" v1="390" v2="391"/>
                <face v3="395" v1="393" v2="394"/>
            </faces>
        </submesh>
    </submeshes>
    <submeshnames>
        <submesh index="0" name="_missing_material_">
        </submesh>
    </submeshnames>
</mesh>